hacapi/__init__.py
hacapi/assignments.py
hacapi/grades.py
hacapi/misc.py
hacapi/payloads.py
hacapi/session.py
home_access_center_api-0.25.7.dist-info/LICENSE
home_access_center_api-0.25.7.dist-info/METADATA
home_access_center_api-0.25.7.dist-info/WHEEL
home_access_center_api-0.25.7.dist-info/top_level.txt
home_access_center_api-0.25.7.dist-info/RECORD
