Metadata-Version: 2.1
Name: home-access-center-api
Version: 0.25.7
Summary: This is a simple API to access the Home Access Center (HAC)
Author-email: Nazchanel <eshaniyer@duck.com>
Project-URL: Homepage, https://github.com/Nazchanel/hac-api
Classifier: Programming Language :: Python :: 3
Classifier: License :: OSI Approved :: MIT License
Classifier: Operating System :: OS Independent
Requires-Python: >=3.7
License-File: LICENSE
